negmas_llm/__init__.py
negmas_llm/components.py
negmas_llm/negotiator.py
negmas_llm/py.typed
negmas_llm-0.2.2.dist-info/WHEEL
negmas_llm-0.2.2.dist-info/METADATA
negmas_llm-0.2.2.dist-info/RECORD
