Metadata-Version: 2.4
Name: negmas-llm
Version: 0.2.2
Summary: LLM-based negotiators for the negmas negotiation framework
Keywords: negotiation,llm,agents,ai,negmas
Author: Yasser Mohammad
Author-email: Yasser Mohammad <yasserfarouk@gmail.com>
License-Expression: AGPL-3.0-or-later
Classifier: Development Status :: 4 - Beta
Classifier: Intended Audience :: Developers
Classifier: Intended Audience :: Science/Research
Classifier: License :: OSI Approved :: GNU Affero General Public License v3 or later (AGPLv3+)
Classifier: Operating System :: OS Independent
Classifier: Programming Language :: Python :: 3
Classifier: Programming Language :: Python :: 3.11
Classifier: Programming Language :: Python :: 3.12
Classifier: Programming Language :: Python :: 3.13
Classifier: Programming Language :: Python :: 3.14
Classifier: Topic :: Scientific/Engineering :: Artificial Intelligence
Requires-Dist: litellm>=1.80.11
Requires-Dist: negmas>=0.14.0
Requires-Dist: pre-commit>=4.5.1 ; extra == 'dev'
Requires-Python: >=3.11
Project-URL: Homepage, https://github.com/autoneg/negmas-llm
Project-URL: Documentation, https://negmas-llm.readthedocs.io
Project-URL: Repository, https://github.com/autoneg/negmas-llm
Project-URL: Issues, https://github.com/autoneg/negmas-llm/issues
Provides-Extra: dev
